shortcircuit/__init__.py
shortcircuit/number5/Number5.py
shortcircuit/number5/Thing.py
shortcircuit/number5/__init__.py
shortcircuit-2022.2.8.1.dist-info/LICENSE
shortcircuit-2022.2.8.1.dist-info/METADATA
shortcircuit-2022.2.8.1.dist-info/WHEEL
shortcircuit-2022.2.8.1.dist-info/top_level.txt
shortcircuit-2022.2.8.1.dist-info/zip-safe
shortcircuit-2022.2.8.1.dist-info/RECORD
