Metadata-Version: 2.1
Name: shortcircuit
Version: 2022.2.8.1
Summary: Python library for a natural language learner AI
Home-page: https://github.com/idin/shortcircuit
Author: Idin
Author-email: py@idin.ca
License: MIT
Keywords: graph computation
Platform: UNKNOWN
Classifier: Development Status :: 3 - Alpha
Classifier: Intended Audience :: Developers
Classifier: Programming Language :: Python :: 3 :: Only
Classifier: Programming Language :: Python :: 3.6
Classifier: Programming Language :: Python :: 3.7
Classifier: Topic :: Software Development :: Libraries :: Python Modules
Requires-Python: ~=3.6
Requires-Dist: pandas
Requires-Dist: pensieve
Requires-Dist: cyberspace
